DINCAE/__init__.py
DINCAE-1.1.0.dist-info/LICENSE.md
DINCAE-1.1.0.dist-info/METADATA
DINCAE-1.1.0.dist-info/WHEEL
DINCAE-1.1.0.dist-info/top_level.txt
DINCAE-1.1.0.dist-info/RECORD
