Metadata-Version: 2.1
Name: DINCAE
Version: 1.1.0
Summary: DINCAE (Data-Interpolating Convolutional Auto-Encoder) is a neural network to reconstruct missing data in satellite observations
Home-page: https://github.com/gher-ulg/DINCAE
Author: Alexander Barth
License: UNKNOWN
Platform: UNKNOWN
Classifier: Programming Language :: Python :: 3
Classifier: License :: OSI Approved :: GNU General Public License v3 or later (GPLv3+)
Classifier: Operating System :: OS Independent
Requires-Python: >=3.6
Requires-Dist: netCDF4 (>=1.4.2)
Requires-Dist: numpy (>=1.15.4)
Requires-Dist: tensorflow (==1.15.2)
Provides-Extra: test
Requires-Dist: pytest-cov ; extra == 'test'
Requires-Dist: codecov ; extra == 'test'
Requires-Dist: pytest ; extra == 'test'
